Workbook

Sheet Sources
A1: DATA SOURCES & VERIFICATION STATUS (v4 — July 2026)
A2: Item | B2: Source / URL | C2: Status
A3: Revenue 2023–2024 | B3: Lufthansa IR key data page. 2024: €37,581M; 2023: €35,442M. URL: https://investor-relations.lufthansagroup.com/en/corporate-facts/key-data/lufthansa-group.html | C3: VERIFIED
A4: Revenue 2022 | B4: LH 2022 Full-Year Results Press Release (03 March 2023): Total revenue = €32,770M (EXACT). URL: https://www.lufthansagroup.com/en/newsroom/releases/lufthansa-group-reports-record-revenue-in-2022.html | C4: VERIFIED
A5: Revenue 2020–2021 | B5: Same LH IR source. 2021: €16,811M; 2020: €13,589M. | C5: VERIFIED
A6: EBIT 2020–2024 | B6: 2024: €1,731M; 2023: €2,669M — LH IR key data page (Reported EBIT). 2022: €1,231M (Reported EBIT) / Adjusted EBIT €1,509M — LH 2022 FY Press Release 03-Mar-2023. Model uses Reported EBIT (€1,231M). Previous value €1,419M was an unverified secondary source figure. 2021: −€1,672M (secondary source ≈ Adjusted EBIT −€1,666M; Reported EBIT was −€2,316M — definitional note: model uses Adjusted-equivalent for 2020-2021, Reported for 2022-2024). 2020: −€5,479M (secondary source). Source: LH IR + 2022 FY Press Release. | C6: APPROXIMATE
A7: Net Income 2024 | B7: LH IR: Net profit 2024 = €1,380M. Updated from initial €1,425M estimate in v1. | C7: VERIFIED
A8: D&A 2020–2024 | B8: 2022: €2,199M — LH 2023 Annual Report comparative CF statement (VERIFIED). 2020-2021: from secondary sources (MacroTrends USD values converted). Verify in AR CF notes. | C8: APPROXIMATE
A9: CapEx 2023–2024 | B9: Gross CapEx: 2024 = €3,743M, 2023 = €3,576M. Source: LH IR key figures. | C9: VERIFIED
A10: Net Debt 2023–2024 | B10: Net indebtedness: 2024 = €5,744M, 2023 = €5,682M. Source: LH IR. | C10: VERIFIED
A11: Total Assets 2022–2024 | B11: 2024: €47,052M; 2023: €45,321M; 2022: €43,335M. LH Annual Reports. | C11: VERIFIED
A12: Total Assets 2020–2021 | B12: 2021: €42,538M — VERIFIED from 2022 FY Press Release (03 March 2023) comparative column. 2020: ~€38,000M — estimated; verify in LH-AR-2020-e.pdf. Source: https://www.lufthansagroup.com/en/newsroom/releases/lufthansa-group-reports-record-revenue-in-2022.html | C12: PARTIALLY VERIFIED
A13: BS equity 2023–2024 | B13: €11,594M (2024), €9,709M (2023). Source: LH IR. | C13: VERIFIED
... A20: Forecast assumptions | B20: Bottom-up estimates: LH management guidance + IATA forecasts + historical trends. See Assumptions rationale column. | C20: ANALYST ESTIMATE
A21: GREEN = verified against LH Annual Reports. AMBER = approximate. ORANGE = estimated — verify before GitHub publish.

Sheet Cover
B2: LUFTHANSA GROUP
B4: Financial Valuation & Forecasting Model | v4.0 (July 2026)
A7: Analyst | B7: Emmanuel Sarpong
A8: Model Version | B8: v4.0 — corrections from primary sources (July 2026)
A9: Currency | B9: EUR (millions)
A10: Fiscal Year | B10: January – December
A11: Data Sources | B11: Lufthansa Group Annual Reports 2020–2024; LH IR Website
A12: Disclaimer | B12: Portfolio project. Not investment advice.
B14: Navigation
B15: → Sources & Verification
B16: → Assumptions + Rationale
B17: → Income Statement
B18: → Balance Sheet
B19: → Cash Flow
B20: → DCF Valuation
B21: → Comparables
B22: → Sensitivity
B23: → Dashboard
B25: v4 changes: 2022 Revenue €32,770M now VERIFIED (LH press release). 2022 EBIT corrected 1,419→1,231 (Reported EBIT). 2021 Total Assets corrected 41,000→42,538. 2022 Equity corrected 5,600→8,500 (OCI pension remeasurement). D&A 2022 corrected 2,142→2,199.

Sheet Assumptions
A1: ASSUMPTIONS — Blue = inputs | Orange = estimates | Yellow = key outputs
A2: Metric | B2: 2020A | C2: 2021A | D2: 2022A | E2: 2023A | F2: 2024A | G2: 2025E | H2: 2026E | I2: 2027E | J2: 2028E | K2: 2029E | L2: 2030E | M2: Rationale
A3: REVENUE & MARGINS | M3: Driver Rationale
A4: Revenue Growth Rate | B4: N/A | C4: 0.237 | D4: 0.949 | E4: 0.082 | F4: 0.061 | G4: 0.05 | H4: 0.04 | I4: 0.04 | J4: 0.03 | K4: 0.03 | L4: 0.025 | M4: 2025E +5%: above LH guidance base; ITA Airways full-year consolidation adds ~€1.5B. 2026-27 +4%: IATA Europe RPK growth forecast 3-5%. 2028-29 +3%: normalization. 2030 +2.5%: near terminal rate.
A5: EBIT Margin | B5: -0.403 | C5: -0.099 | D5: 0.0376 | E5: 0.075 | F5: 0.046 | G5: 0.055 | H5: 0.06 | I5: 0.065 | J5: 0.068 | K5: 0.07 | L5: 0.07 | M5: 2025E 5.5%: recovery from 4.6% in 2024 (strikes cost ~€450M). Mgmt targets 8%+ adj. EBIT margin by 2028 (reported margin lags ~2-3pp). 2030 at 7.0%: conservative vs target, reflecting execution risk.
A6: D&A (€M) | B6: 2088 | C6: 2107 | D6: 2199 | E6: 2228 | F6: 2337 | G6: 2380 | H6: 2430 | I6: 2480 | J6: 2530 | K6: 2580 | L6: 2630 | M6: 2022: €2,199M (LH 2023 AR comparative CF statement). 2021: €2,107M (secondary source — verify in LH-AR-2021-e.pdf CF statement). 2020: €2,088M (secondary source; note: 2020 included large aircraft impairments in the P&L but D&A line in CF is the recurring depreciation figure). Forecast grows ~€50M/yr tracking fleet CapEx cycle.
A7: Capital Expenditure (€M) | B7: N/A | C7: N/A | D7: N/A | E7: 3576 | F7: 3743 | G7: 3600 | H7: 3500 | I7: 3400 | J7: 3300 | K7: 3200 | L7: 3100 | M7: 2023-24 verified from LH IR. Forecast declines €3,600M→€3,100M as near-term fleet renewal cycle peaks. LH guided €3-4B CapEx p.a. through 2028.
A8: Interest Expense (€M) | B8: see IS | C8: see IS | D8: see IS | E8: see IS | F8: see IS | G8: 300 | H8: 280 | I8: 260 | J8: 250 | K8: 240 | L8: 230 | M8: 2024 interest ~€349M. Declining as net debt reduces. LH targets net debt/EBITDA < 3.5x.
A9: Tax Rate | B9: 0.25 | C9: 0.25 | D9: 0.25 | E9: 0.25 | F9: 0.25 | G9: 0.25 | H9: 0.25 | I9: 0.25 | J9: 0.25 | K9: 0.25 | L9: 0.25 | M9: German combined rate ~30%. Used 25% (conservative) reflecting deferred tax benefits and lower-rate foreign subsidiaries.
A11: WACC BUILD-UP
A12: Risk-Free Rate (Rf) | B12: 0.025 | M12: 10Y German Bund yield avg 2024 ≈ 2.3–2.6%. Used 2.5%. Source: Deutsche Bundesbank.
A13: Equity Risk Premium (ERP) | B13: 0.055 | M13: Damodaran Western Europe ERP (Jan 2024): ~5.5%. Source: pages.stern.nyu.edu/~adamodar/
A14: Beta (Levered, 5Y monthly) | B14: 1.2 | M14: LHA.DE 5Y monthly beta vs STOXX 600 ≈ 1.1–1.3. Used 1.20 (midpoint).
A15: Cost of Equity [Rf + β × ERP] | B15: =B12+B14*B13 | M15: Ke = 2.5% + 1.20 × 5.5% = 9.1% (CAPM)
A16: Pre-Tax Cost of Debt (Kd) | B16: 0.035 | M16: Based on LH bond yields 2024 (~3–4% coupon). Used 3.5%. LH rating: Baa3/BBB-.
A17: Tax Rate (for Kd shield) | B17: 0.25
A18: After-Tax Cost of Debt [Kd × (1-t)] | B18: =B16*(1-B17) | M18: Kd(AT) = 3.5% × 75% = 2.625%
A19: Weight of Equity (We) | B19: 0.7
A20: Weight of Debt (Wd) | B20: 0.3
A21: WACC [We × Ke + Wd × Kd(AT)] | B21: =B19*B15+B20*B18 | M21: WACC = 70% × 9.1% + 30% × 2.625% ≈ 7.16%. Peer airline range 7-10%. Lower end justified by LH's scale and IG rating.
A22: Terminal Growth Rate (g) | B22: 0.02 | M22: 2.0%. EU long-run nominal GDP ≈ 2.5% (ECB). Used 2.0% — conservative for aviation's capital intensity. Must remain below WACC. Sensitivity table: 1.0–4.0%.
A24: VALUATION BRIDGE INPUTS
A25: Net Debt (€M, 2024A — verified) | B25: 5744 | M25: LH IR: Net indebtedness 2024 = €5,744M. VERIFIED.
A26: Shares Outstanding (M) | B26: 2375 | M26: ~2,375M shares (2024 year-end). Verify against LH AR 2024 issued capital note.
A27: Current Share Price (€) — for upside calc | B27: 6.18 | M27: LH IR: LHA.DE year-end 2024 = €6.18. VERIFIED.
A28: Dividends Per Share (€) — declared | B28: 0 | C28: 0 | D28: 0 | E28: 0.3 | F28: 0.3 | G28: 0.33 | H28: 0.36 | I28: 0.4 | J28: 0.44 | K28: 0.48 | L28: 0.5 | M28: LH resumed dividends for FY2023 (€0.30/share, paid at AGM May 2024). FY2024: approx €0.30 (guided). 2025E: LH guided ~€0.33. Forecast grows modestly to €0.50 by 2030. Total annual dividend = DPS × 2,375M shares ≈ €700-1,190M. Source: LH IR press releases.

Sheet Income Statement
A1: INCOME STATEMENT (€ millions) | v4: 2022 figures corrected from official LH press release (03-Mar-2023)
B2: 2020A | C2: 2021A | D2: 2022A | E2: 2023A | F2: 2024A | G2: 2025E | H2: 2026E | I2: 2027E | J2: 2028E | K2: 2029E | L2: 2030E
A3: Revenue | B3: 13589 | C3: 16811 | D3: 32770 | E3: 35442 | F3: 37581 | G3: =F3*(1+Assumptions!G4) | H3: =G3*(1+Assumptions!H4) | I3: =H3*(1+Assumptions!I4) | J3: =I3*(1+Assumptions!J4) | K3: =J3*(1+Assumptions!K4) | L3: =K3*(1+Assumptions!L4)
A4: EBIT | B4: -5479 | C4: -1672 | D4: 1231 | E4: 2669 | F4: 1731 | G4: =G3*Assumptions!G5 | H4: =H3*Assumptions!H5 | I4: =I3*Assumptions!I5 | J4: =J3*Assumptions!J5 | K4: =K3*Assumptions!K5 | L4: =L3*Assumptions!L5
A5: Depreciation & Amortisation (D&A) | B5: =Assumptions!B6 | C5: =Assumptions!C6 | D5: =Assumptions!D6 | E5: =Assumptions!E6 | F5: =Assumptions!F6 | G5: =Assumptions!G6 | H5: =Assumptions!H6 | I5: =Assumptions!I6 | ... L5: =Assumptions!L6
A6: EBITDA | B6: =B4+B5 | C6: =C4+C5 | D6: =D4+D5 | E6: =E4+E5 | F6: =F4+F5 | G6: =G4+G5 | H6: =H4+H5 | I6: =I4+I5 | ... L6: =L4+L5
A7: Interest Expense | B7: 557 | C7: 440 | D7: 396 | E7: 380 | F7: 349 | G7: =Assumptions!G8 | H7: =Assumptions!H8 | I7: =Assumptions!I8 | J7: =Assumptions!J8 | K7: =Assumptions!K8 | L7: =Assumptions!L8
A8: EBT (Earnings Before Tax) | B8: =B4-B7 | C8: =C4-C7 | D8: =D4-D7 | E8: =E4-E7 | F8: =F4-F7 | G8: =G4-G7 | H8: =H4-H7 | I8: =I4-I7 | ... L8: =L4-L7
A9: Tax Expense / (Benefit) | B9: =MAX(B8*Assumptions!B9,0) | C9: =MAX(C8*Assumptions!C9,0) | D9: =MAX(D8*Assumptions!D9,0) | E9: =MAX(E8*Assumptions!E9,0) | F9: =MAX(F8*Assumptions!F9,0) | G9: =MAX(G8*Assumptions!G9,0) | H9: =MAX(H8*Assumptions!H9,0) | I9: =MAX(I8*Assumptions!I9,0) | ... L9: =MAX(L8*Assumptions!L9,0)
A10: Net Income | B10: -6724 | C10: -1993 | D10: 791 | E10: 1666 | F10: 1380 | G10: =G8-G9 | H10: =H8-H9 | I10: =I8-I9 | J10: =J8-J9 | K10: =K8-K9 | L10: =L8-L9
A12: MARGINS
A13: EBIT Margin | B13: =IFERROR(B4/B3,"-") | C13: =IFERROR(C4/C3,"-") | D13: =IFERROR(D4/D3,"-") | E13: =IFERROR(E4/E3,"-") | F13: =IFERROR(F4/F3,"-") | G13: =IFERROR(G4/G3,"-") | H13: =IFERROR(H4/H3,"-") | I13: =IFERROR(I4/I3,"-") | ... L13: =IFERROR(L4/L3,"-")
A14: EBITDA Margin | B14: =IFERROR(B6/B3,"-") | C14: =IFERROR(C6/C3,"-") | D14: =IFERROR(D6/D3,"-") | E14: =IFERROR(E6/E3,"-") | F14: =IFERROR(F6/F3,"-") | G14: =IFERROR(G6/G3,"-") | H14: =IFERROR(H6/H3,"-") | I14: =IFERROR(I6/I3,"-") | ... L14: =IFERROR(L6/L3,"-")
A15: Net Margin | B15: =IFERROR(B10/B3,"-") | C15: =IFERROR(C10/C3,"-") | D15: =IFERROR(D10/D3,"-") | E15: =IFERROR(E10/E3,"-") | F15: =IFERROR(F10/F3,"-") | G15: =IFERROR(G10/G3,"-") | H15: =IFERROR(H10/H3,"-") | I15: =IFERROR(I10/I3,"-") | ... L15: =IFERROR(L10/L3,"-")
A17: VERIFIED: 2024 Revenue €37,581M; 2023 €35,442M; 2024 EBIT €1,731M; 2024 Net Income €1,380M. Source: LH IR. VERIFIED: 2022 Revenue €32,770M (EXACT — LH 2022 FY press release 03-Mar-2023). VERIFIED: 2022 EBIT €1,231M (Reported EBIT — same press release; Adjusted EBIT = €1,509M). NOTE on 2021 EBIT (−€1,672M): secondary source figure approximating Adjusted EBIT (press release shows Reported EBIT 2021 = −€2,316M, Adjusted EBIT = −€1,666M). Definitional note added to Sources sheet.

Sheet Balance Sheet
A1: BALANCE SHEET (€ millions) | v3: Current liabilities independently modelled — balance check is genuine | Orange = estimated
B2: 2020A | C2: 2021A | D2: 2022A | E2: 2023A | F2: 2024A | G2: 2025E | H2: 2026E | I2: 2027E | J2: 2028E | K2: 2029E | L2: 2030E
A3: NON-CURRENT ASSETS
A4: Aircraft & Reserve Engines | B4: 0 | C4: 0 | D4: 0 | E4: 17464 | F4: 18828 | G4: =F4*(1+Assumptions!G4*0.6) | H4: =G4*(1+Assumptions!H4*0.6) | I4: =H4*(1+Assumptions!I4*0.6) | J4: =I4*(1+Assumptions!J4*0.6) | K4: =J4*(1+Assumptions!K4*0.6) | L4: =K4*(1+Assumptions!L4*0.6)
A5: Other PP&E, Intangibles & Right-of-Use | B5: 0 | C5: 0 | D5: 0 | E5: 11884 | F5: 11908 | G5: =F5*1.01 | H5: =G5*1.01 | I5: =H5*1.01 | J5: =I5*1.01 | K5: =J5*1.01 | L5: =K5*1.01
A6: Total Non-Current Assets | B6: 26500 | C6: 27500 | D6: 28000 | E6: 29348 | F6: 30736 | G6: =SUM(G4:G5) | H6: =SUM(H4:H5) | I6: =SUM(I4:I5) | J6: =SUM(J4:J5) | K6: =SUM(K4:K5) | L6: =SUM(L4:L5)
A7: CURRENT ASSETS
A8: Cash & Cash Equivalents [→ CF waterfall row 28] | B8: 2500 | C8: 2200 | D8: 2800 | E8: 3900 | F8: 3500 | G8: ='Cash Flow'!G28 | H8: ='Cash Flow'!H28 | I8: ='Cash Flow'!I28 | J8: ='Cash Flow'!J28 | K8: ='Cash Flow'!K28 | L8: ='Cash Flow'!L28
A9: Trade & Other Receivables | B9: 2500 | C9: 2800 | D9: 3100 | E9: 3500 | F9: 3600 | G9: ='Income Statement'!G3*0.035 | H9: ='Income Statement'!H3*0.035 | I9: ='Income Statement'!I3*0.035 | J9: ='Income Statement'!J3*0.035 | K9: ='Income Statement'!K3*0.035 | L9: ='Income Statement'!L3*0.035
A10: Other Current Assets | B10: 5000 | C10: 5000 | D10: 5000 | E10: 5000 | F10: 5000 | G10: =5000 | H10: =5000 | I10: =5000 | J10: =5000 | K10: =5000 | L10: =5000
A11: Total Current Assets | B11: 11500 | C11: 13500 | D11: 15335 | E11: 15973 | F11: 16316 | G11: =SUM(G8:G10) | H11: =SUM(H8:H10) | I11: =SUM(I8:I10) | J11: =SUM(J8:J10) | K11: =SUM(K8:K10) | L11: =SUM(L8:L10)
A12: TOTAL ASSETS | B12: 38000 | C12: 42538 | D12: 43335 | E12: 45321 | F12: 47052 | G12: =G6+G11 | H12: =H6+H11 | I12: =I6+I11 | J12: =J6+J11 | K12: =K6+K11 | L12: =L6+L11
A14: EQUITY
A15: Shareholders' Equity [Prior + Net Income − Dividends] | B15: -2000 | C15: 4490 | D15: 8500 | E15: 9709 | F15: 11594 | G15: =F15+'Income Statement'!G10-(Assumptions!G28*Assumptions!B26) | H15: =G15+'Income Statement'!H10-(Assumptions!H28*Assumptions!B26) | I15: =H15+'Income Statement'!I10-(Assumptions!I28*Assumptions!B26) | J15: =I15+'Income Statement'!J10-(Assumptions!J28*Assumptions!B26) | K15: =J15+'Income Statement'!K10-(Assumptions!K28*Assumptions!B26) | L15: =K15+'Income Statement'!L10-(Assumptions!L28*Assumptions!B26)
A16: NON-CURRENT LIABILITIES
A17: Long-Term Borrowings | B17: 18000 | C17: 18000 | D17: 16000 | E17: 13000 | F17: 11413 | G17: =MAX(F17-'Cash Flow'!G13*0.4,6000) | H17: =MAX(G17-'Cash Flow'!H13*0.4,6000) | I17: =MAX(H17-'Cash Flow'!I13*0.4,6000) | J17: =MAX(I17-'Cash Flow'!J13*0.4,6000) | K17: =MAX(J17-'Cash Flow'!K13*0.4,6000) | L17: =MAX(K17-'Cash Flow'!L13*0.4,6000)
A18: Pension Obligations | B18: 5000 | C18: 4500 | D18: 3500 | E18: 2676 | F18: 2566 | G18: =F18*0.97 | H18: =G18*0.97 | I18: =H18*0.97 | J18: =I18*0.97 | K18: =J18*0.97 | L18: =K18*0.97
A19: Other Non-Current Liabilities | B19: 1500 | C19: 1500 | D19: 1500 | E19: 1500 | F19: 1500 | G19: =1500 | H19: =1500 | I19: =1500 | J19: =1500 | K19: =1500 | L19: =1500
A20: Total Non-Current Liabilities | B20: =SUM(B17:B19) | C20: =SUM(C17:C19) | D20: =SUM(D17:D19) | E20: =SUM(E17:E19) | F20: =SUM(F17:F19) | G20: =SUM(G17:G19) | H20: =SUM(H17:H19) | I20: =SUM(I17:I19) | ... L20: =SUM(L17:L19)
A21: CURRENT LIABILITIES
A22: Current Borrowings & Provisions | B22: 3000 | C22: 3000 | D22: 3000 | E22: 3000 | F22: 3000 | G22: =3000 | H22: =3000 | I22: =3000 | J22: =3000 | K22: =3000 | L22: =3000
A23: Trade Payables [= Revenue × 4.5%] | B23: 600 | C23: 750 | D23: 1450 | E23: 1600 | F23: 1700 | G23: ='Income Statement'!G3*0.045 | H23: ='Income Statement'!H3*0.045 | I23: ='Income Statement'!I3*0.045 | J23: ='Income Statement'!J3*0.045 | K23: ='Income Statement'!K3*0.045 | L23: ='Income Statement'!L3*0.045
A24: Deferred Revenue (advance ticket sales) [= Revenue × 9.0%] | B24: 1200 | C24: 1500 | D24: 2900 | E24: 3200 | F24: 3400 | G24: ='Income Statement'!G3*0.09 | H24: ='Income Statement'!H3*0.09 | I24: ='Income Statement'!I3*0.09 | J24: ='Income Statement'!J3*0.09 | K24: ='Income Statement'!K3*0.09 | L24: ='Income Statement'!L3*0.09
A25: Other Current Liabilities [= Revenue × 8.0%] | B25: 1100 | C25: 1300 | D25: 2600 | E25: 2800 | F25: 3000 | G25: ='Income Statement'!G3*0.08 | H25: ='Income Statement'!H3*0.08 | I25: ='Income Statement'!I3*0.08 | J25: ='Income Statement'!J3*0.08 | K25: ='Income Statement'!K3*0.08 | L25: ='Income Statement'!L3*0.08
A26: Total Current Liabilities | B26: =SUM(B22:B25) | C26: =SUM(C22:C25) | D26: =SUM(D22:D25) | E26: =SUM(E22:E25) | F26: =SUM(F22:F25) | G26: =SUM(G22:G25) | H26: =SUM(H22:H25) | I26: =SUM(I22:I25) | ... L26: =SUM(L22:L25)
A27: TOTAL EQUITY & LIABILITIES | B27: =B15+B20+B26 | C27: =C15+C20+C26 | D27: =D15+D20+D26 | E27: =E15+E20+E26 | F27: =F15+F20+F26 | G27: =G15+G20+G26 | H27: =H15+H20+H26 | I27: =I15+I20+I26 | ... L27: =L15+L20+L26
A28: Balance Check (TA − TE&L) ← non-zero in historical (estimated inputs) | B28: =B12-B27 | C28: =C12-C27 | D28: =D12-D27 | E28: =E12-E27 | F28: =F12-F27 | G28: =G12-G27 | H28: =H12-H27 | I28: =I12-I27 | ... L28: =L12-L27
A30: v4 Balance Sheet corrections (from LH 2022 FY Press Release, 03-Mar-2023): • 2021 Total Assets updated 41,000 → 42,538 (now VERIFIED from press release comparative column). • 2022 Equity updated 5,600 → 8,500 (press release: 'almost doubled to €8.5bn on Dec 31 2022'). The jump from ~€4.5bn (2021) to ~€8.5bn (2022) is driven by OCI pension remeasurement — net pension obligations fell from ~€6.5bn to ~€2.0bn in 2022, flowing through OCI, not P&L. A simplified IS-based model cannot capture this via Net Income alone — cell kept orange (estimated). • 2022 EBIT corrected to €1,231M (Reported EBIT, same press release). See IS sheet. v3 structural changes still apply: • Cash (row 8) forecast driven from CF waterfall row 28 — genuine 3-statement link. • Equity (row 15) forecast = Prior + Net Income − (DPS × shares). LH resumed dividends 2023. • Current Liabilities (rows 23-25): independently modelled, balance check is genuine. VERIFIED items (2023-24): Total Assets (47,052 / 45,321), NCA (30,736 / 29,348), Aircraft (18,828 / 17,464), Equity (11,594 / 9,709), LT Borrowings 2024 (11,413), Pensions (2,566 / 2,676). Source: LH Annual Report 2024.

Sheet Cash Flow
A1: CASH FLOW STATEMENT (€ millions) | Section A: FCFF (for DCF) | Section B: Cash Waterfall (for Balance Sheet)
B2: 2020A | C2: 2021A | D2: 2022A | E2: 2023A | F2: 2024A | G2: 2025E | H2: 2026E | I2: 2027E | J2: 2028E | K2: 2029E | L2: 2030E
A3: SECTION A — FREE CASH FLOW TO FIRM (FCFF) [used for DCF valuation]
A4: EBIT | B4: ='Income Statement'!B4 | C4: ='Income Statement'!C4 | D4: ='Income Statement'!D4 | E4: ='Income Statement'!E4 | F4: ='Income Statement'!F4 | G4: ='Income Statement'!G4 | H4: ='Income Statement'!H4 | I4: ='Income Statement'!I4 | ... L4: ='Income Statement'!L4
A5: Add: D&A | B5: ='Income Statement'!B5 | C5: ='Income Statement'!C5 | D5: ='Income Statement'!D5 | E5: ='Income Statement'!E5 | F5: ='Income Statement'!F5 | G5: ='Income Statement'!G5 | H5: ='Income Statement'!H5 | I5: ='Income Statement'!I5 | ... L5: ='Income Statement'!L5
A6: Less: Tax Paid | B6: =-'Income Statement'!B9 | C6: =-'Income Statement'!C9 | D6: =-'Income Statement'!D9 | E6: =-'Income Statement'!E9 | F6: =-'Income Statement'!F9 | G6: =-'Income Statement'!G9 | H6: =-'Income Statement'!H9 | I6: =-'Income Statement'!I9 | ... L6: =-'Income Statement'!L9
A7: Change in Working Capital (–ΔRevenue × 2%) | B7: -800 | C7: 200 | D7: -1200 | E7: 600 | F7: -400 | G7: =-('Income Statement'!G3-'Income Statement'!F3)*0.02 | H7: =-('Income Statement'!H3-'Income Statement'!G3)*0.02 | I7: =-('Income Statement'!I3-'Income Statement'!H3)*0.02 | J7: =-('Income Statement'!J3-'Income Statement'!I3)*0.02 | K7: =-('Income Statement'!K3-'Income Statement'!J3)*0.02 | L7: =-('Income Statement'!L3-'Income Statement'!K3)*0.02
A8: Operating CF (pre-interest, for FCFF) | B8: =SUM(B4:B7) | C8: =SUM(C4:C7) | D8: =SUM(D4:D7) | E8: =SUM(E4:E7) | F8: =SUM(F4:F7) | G8: =SUM(G4:G7) | H8: =SUM(H4:H7) | I8: =SUM(I4:I7) | ... L8: =SUM(L4:L7)
A9: INVESTING CASH FLOW (CapEx)
A10: Capital Expenditure (–CapEx) | B10: =IFERROR(-Assumptions!B7,0) | C10: =IFERROR(-Assumptions!C7,0) | D10: =IFERROR(-Assumptions!D7,0) | E10: =IFERROR(-Assumptions!E7,0) | F10: =IFERROR(-Assumptions!F7,0) | G10: =IFERROR(-Assumptions!G7,0) | H10: =IFERROR(-Assumptions!H7,0) | I10: =IFERROR(-Assumptions!I7,0) | ... L10: =IFERROR(-Assumptions!L7,0)
A11: Investing Cash Flow | B11: =B10 | C11: =C10 | D11: =D10 | E11: =E10 | F11: =F10 | G11: =G10 | H11: =H10 | I11: =I10 | ... L11: =L10
A12: FCFF = EBIT(1–t) + D&A − CapEx − ΔNWC
A13: FCFF (€M) | B13: =B4*(1-Assumptions!B9)+B5+B10+B7 | C13: =C4*(1-Assumptions!C9)+C5+C10+C7 | D13: =D4*(1-Assumptions!D9)+D5+D10+D7 | E13: =E4*(1-Assumptions!E9)+E5+E10+E7 | F13: =F4*(1-Assumptions!F9)+F5+F10+F7 | G13: =G4*(1-Assumptions!G9)+G5+G10+G7 | H13: =H4*(1-Assumptions!H9)+H5+H10+H7 | I13: =I4*(1-Assumptions!I9)+I5+I10+I7 | ... L13: =L4*(1-Assumptions!L9)+L5+L10+L7
A15: SECTION A — FCFF: FCFF = EBIT × (1–t) + D&A − CapEx − ΔNWC. Used exclusively for DCF valuation (pre-interest, unlevered). FCFF ≠ operating CF: FCFF starts from EBIT (pre-interest) while operating CF starts from Net Income (post-interest, post-tax). 2024 verified operating CF: €3,892M (LH IR). See Section B below for the post-interest cash waterfall that drives the Balance Sheet cash balance.
A17: SECTION B — BALANCE SHEET CASH WATERFALL (indirect method, post-interest) [drives BS row 8 cash]
A18: Net Income (post-interest, post-tax) | B18: ='Income Statement'!B10 | C18: ='Income Statement'!C10 | D18: ='Income Statement'!D10 | E18: ='Income Statement'!E10 | F18: ='Income Statement'!F10 | G18: ='Income Statement'!G10 | H18: ='Income Statement'!H10 | I18: ='Income Statement'!I10 | ... L18: ='Income Statement'!L10
A19: Add: D&A (non-cash) | B19: ='Income Statement'!B5 | C19: ='Income Statement'!C5 | D19: ='Income Statement'!D5 | E19: ='Income Statement'!E5 | F19: ='Income Statement'!F5 | G19: ='Income Statement'!G5 | H19: ='Income Statement'!H5 | I19: ='Income Statement'!I5 | ... L19: ='Income Statement'!L5
A20: Change in Working Capital | B20: -800 | C20: 200 | D20: -1200 | E20: 600 | F20: -400 | G20: =-('Income Statement'!G3-'Income Statement'!F3)*0.02 | H20: =-('Income Statement'!H3-'Income Statement'!G3)*0.02 | I20: =-('Income Statement'!I3-'Income Statement'!H3)*0.02 | J20: =-('Income Statement'!J3-'Income Statement'!I3)*0.02 | K20: =-('Income Statement'!K3-'Income Statement'!J3)*0.02 | L20: =-('Income Statement'!L3-'Income Statement'!K3)*0.02
A21: Operating Cash Flow (indirect, post-interest) | B21: =SUM(B18:B20) | C21: =SUM(C18:C20) | D21: =SUM(D18:D20) | E21: =SUM(E18:E20) | F21: =SUM(F18:F20) | G21: =SUM(G18:G20) | H21: =SUM(H18:H20) | I21: =SUM(I18:I20) | ... L21: =SUM(L18:L20)
A22: Capital Expenditure (–CapEx) | B22: =IFERROR(-Assumptions!B7,0) | C22: =IFERROR(-Assumptions!C7,0) | D22: =IFERROR(-Assumptions!D7,0) | E22: =IFERROR(-Assumptions!E7,0) | F22: =IFERROR(-Assumptions!F7,0) | G22: =IFERROR(-Assumptions!G7,0) | H22: =IFERROR(-Assumptions!H7,0) | I22: =IFERROR(-Assumptions!I7,0) | ... L22: =IFERROR(-Assumptions!L7,0)
A23: Dividends Paid [= –DPS × Shares] | B23: 0 | C23: 0 | D23: 0 | E23: 0 | F23: -713 | G23: =-(Assumptions!G28*Assumptions!B26) | H23: =-(Assumptions!H28*Assumptions!B26) | I23: =-(Assumptions!I28*Assumptions!B26) | J23: =-(Assumptions!J28*Assumptions!B26) | K23: =-(Assumptions!K28*Assumptions!B26) | L23: =-(Assumptions!L28*Assumptions!B26)
A24: Net Debt Repaid / (Drawn) [–ve = repayment] | B24: 5000 | C24: 0 | D24: -2000 | E24: -3000 | F24: -1587 | G24: ='Balance Sheet'!G17-'Balance Sheet'!F17 | H24: ='Balance Sheet'!H17-'Balance Sheet'!G17 | I24: ='Balance Sheet'!I17-'Balance Sheet'!H17 | J24: ='Balance Sheet'!J17-'Balance Sheet'!I17 | K24: ='Balance Sheet'!K17-'Balance Sheet'!J17 | L24: ='Balance Sheet'!L17-'Balance Sheet'!K17
A25: Financing Cash Flow [Dividends + Net Debt Change] | B25: =B23+B24 | C25: =C23+C24 | D25: =D23+D24 | E25: =E23+E24 | F25: =F23+F24 | G25: =G23+G24 | H25: =H23+H24 | I25: =I23+I24 | ... L25: =L23+L24
A26: Net Change in Cash | B26: =B21+B22+B25 | C26: =C21+C22+C25 | D26: =D21+D22+D25 | E26: =E21+E22+E25 | F26: =F21+F22+F25 | G26: =G21+G22+G25 | H26: =H21+H22+H25 | I26: =I21+I22+I25 | ... L26: =L21+L22+L25
A27: Beginning Cash (start of year) | B27: 3000 | C27: 2500 | D27: 2200 | E27: 2800 | F27: 3900 | G27: ='Balance Sheet'!F8 | H27: ='Cash Flow'!G28 | I27: ='Cash Flow'!H28 | J27: ='Cash Flow'!I28 | K27: ='Cash Flow'!J28 | L27: ='Cash Flow'!K28
A28: Ending Cash [→ Balance Sheet row 8] | B28: =B27+B26 | C28: =C27+C26 | D28: =D27+D26 | E28: =E27+E26 | F28: =F27+F26 | G28: =G27+G26 | H28: =H27+H26 | I28: =I27+I26 | ... L28: =L27+L26
A30: SECTION B — Why two CF sections? Section A (FCFF) starts from EBIT (pre-interest) to get an unlevered cash flow for DCF. Section B starts from Net Income (post-interest, post-tax) — the indirect method used for balance sheet integration. Both give related but distinct measures. Section B ending cash (row 28) drives Balance Sheet row 8 (Cash & Equivalents) for forecast years, creating a genuine 3-statement link: Income Statement → Cash Flow → Balance Sheet. Note: Historical CF waterfall may not exactly reconcile (estimated inputs). Forecast years should balance if assumptions are consistent.

Sheet DCF Valuation
A1: DCF VALUATION (€ millions) — FCFF approach, Gordon Growth terminal value
B2: 2025E | C2: 2026E | D2: 2027E | E2: 2028E | F2: 2029E | G2: 2030E
A3: PROJECTED FCFF (linked from Cash Flow sheet, Section A)
A4: FCFF (€M) | B4: ='Cash Flow'!G13 | C4: ='Cash Flow'!H13 | D4: ='Cash Flow'!I13 | E4: ='Cash Flow'!J13 | F4: ='Cash Flow'!K13 | G4: ='Cash Flow'!L13
A5: Discount Period (t = year 1–6) | B5: 1 | C5: 2 | D5: 3 | E5: 4 | F5: 5 | G5: 6
A6: Discount Factor [1 ÷ (1+WACC)^t] | B6: =1/(1+Assumptions!B21)^B5 | C6: =1/(1+Assumptions!B21)^C5 | D6: =1/(1+Assumptions!B21)^D5 | E6: =1/(1+Assumptions!B21)^E5 | F6: =1/(1+Assumptions!B21)^F5 | G6: =1/(1+Assumptions!B21)^G5
A7: PV of FCFF | B7: =B4*B6 | C7: =C4*C6 | D7: =D4*D6 | E7: =E4*E6 | F7: =F4*F6 | G7: =G4*G6
A9: TERMINAL VALUE (Gordon Growth Model)
A10: Terminal Year FCFF (2030E) | B10: ='Cash Flow'!L13
A11: WACC (from Assumptions) | B11: =Assumptions!B21
A12: Terminal Growth Rate g (from Assumptions) | B12: =Assumptions!B22
A13: Terminal Value = FCFF₂₀₃₀ × (1+g) ÷ (WACC − g) | B13: =B10*(1+B12)/(B11-B12)
A14: PV of Terminal Value [TV ÷ (1+WACC)^6] | B14: =B13/(1+Assumptions!B21)^6 | C14: ← Gordon Growth: WACC must exceed g. Verified: 7.16% > 2.0%.
A16: EQUITY BRIDGE
A17: Sum of PV FCFFs (explicit period) | B17: =SUM(B7:G7)
A18: PV of Terminal Value | B18: =B14
A19: Enterprise Value (EV) | B19: =B17+B18
A20: Less: Net Debt (2024A verified) | B20: =Assumptions!B25
A21: Equity Value | B21: =B19-B20
A22: Shares Outstanding (M) | B22: =Assumptions!B26
A23: Implied Share Price (€) | B23: =B21/B22
A24: Reference: Year-End 2024 Price (€) | B24: =Assumptions!B27
A25: DCF Upside / (Downside) | B25: =(B23-B24)/B24
A26: Terminal Value as % of EV | B26: =B18/B19
A28: FCFF chosen over FCFE: LH has significant debt (net debt €5.7B). FCFF values the whole firm independently of capital structure, then subtracts net debt for equity value. More stable than FCFE when leverage changes. WACC: Ke=9.1% (CAPM: 2.5% + 1.20×5.5%), Kd(AT)=2.6% (3.5%×75%), 70/30 target weights → WACC≈7.16%. Terminal growth 2.0%: below EU nominal GDP ~2.5%, conservative for capital-intensive legacy carrier.

Sheet Comparables
A1: COMPARABLE COMPANY ANALYSIS — FY2024 Financials | Market caps: approximate Q4 2024
A2: Company | B2: Mkt Cap (€M) | C2: Net Debt (€M) | D2: EV (€M) | E2: Revenue (€M) | F2: EBITDA (€M) | G2: EV/EBITDA | H2: P/E
A3: Lufthansa | B3: 15400 | C3: 5744 | D3: =B3+C3 | E3: 37581 | F3: 4068 | G3: =D3/F3 | H3: 11.2
A4: Ryanair | B4: 24500 | C4: -3200 | D4: =B4+C4 | E4: 14000 | F4: 4300 | G4: =D4/F4 | H4: 14.8
A5: IAG | B5: 14500 | C5: 7800 | D5: =B5+C5 | E5: 29900 | F5: 5800 | G5: =D5/F5 | H5: 9.1
A6: Air France-KLM | B6: 4200 | C6: 9000 | D6: =B6+C6 | E6: 31000 | F6: 5000 | G6: =D6/F6 | H6: 7.2
A7: easyJet | B7: 5200 | C7: 1500 | D7: =B7+C7 | E7: 10100 | F7: 1900 | G7: =D7/F7 | H7: 12.5
A8: Median (excl. Lufthansa) | B8: =MEDIAN(B4:B7) | C8: =MEDIAN(C4:C7) | E8: =MEDIAN(E4:E7) | F8: =MEDIAN(F4:F7) | G8: =MEDIAN(G4:G7) | H8: =MEDIAN(H4:H7)
A9: ⚠ Market caps approximate Q4 2024. Re-verify before presentation. IAG in GBP → converted ~1.18 GBPEUR. Revenue and EBITDA: FY2024 reported from company IR / annual reports. Source: company IR pages, Bloomberg proxy.
A12: MULTIPLE-BASED VALUATION — EV/EBITDA
A13: Lufthansa EBITDA (2024A verified) | B13: ='Income Statement'!F6
A14: Median EV/EBITDA (ex-LH) | B14: =G8
A15: Implied EV | B15: =B13*B14
A16: Less: Net Debt (2024A verified) | B16: =Assumptions!B25
A17: Implied Equity Value | B17: =B15-B16
A18: Implied Share Price — Comps (€) | B18: =B17/Assumptions!B26

Sheet Sensitivity
A1: SENSITIVITY — Implied Share Price (€) | WACC × Terminal Growth Rate | Base case highlighted
A3: WACC \ TGR | B3: 0.01 | C3: 0.015 | D3: 0.02 | E3: 0.025 | F3: 0.03 | G3: 0.035 | H3: 0.04
A4: 0.06 | B4: =IF($A4<=B$3,"N/A",('Cash Flow'!G13/(1+$A4)^1+'Cash Flow'!H13/(1+$A4)^2+'Cash Flow'!I13/(1+$A4)^3+'Cash Flow'!J13/(1+$A4)^4+'Cash Flow'!K13/(1+$A4)^5+'Cash Flow'!L13/(1+$A4)^6+('Cash Flow'!L13*(1+B$3)/($A4-B$3))/(1+$A4)^6-Assumptions!B25)/Assumptions!B26) | C4: =IF($A4<=C$3,"N/A",('Cash Flow'!G13/(1+$A4)^1+'Cash Flow'!H13/(1+$A4)^2+'Cash Flow'!I13/(1+$A4)^3+'Cash Flow'!J13/(1+$A4)^4+'Cash Flow'!K13/(1+$A4)^5+'Cash Flow'!L13/(1+$A4)^6+('Cash Flow'!L13*(1+C$3)/($A4-C$3))/(1+$A4)^6-Assumptions!B25)/Assumptions!B26) | D4: =IF($A4<=D$3,"N/A",('Cash Flow'!G13/(1+$A4)^1+'Cash Flow'!H13/(1+$A4)^2+'Cash Flow'!I13/(1+$A4)^3+'Cash Flow'!J13/(1+$A4)^4+'Cash Flow'!K13/(1+$A4)^5+'Cash Flow'!L13/(1+$A4)^6+('Cash Flow'!L13*(1+D$3)/($A4-D$3))/(1+$A4)^6-Assumptions!B25)/Assumptions!B26) | E4: =IF($A4<=E$3,"N/A",('Cash Flow'!G13/(1+$A4)^1+'Cash Flow'!H13/(1+$A4)^2+'Cash Flow'!I13/(1+$A4)^3+'Cash Flow'!J13/(1+$A4)^4+'Cash Flow'!K13/(1+$A4)^5+'Cash Flow'!L13/(1+$A4)^6+('Cash Flow'!L13*(1+E$3)/($A4-E$3))/(1+$A4)^6-Assumptions!B25)/Assumptions!B26) | F4: =IF($A4<=F$3,"N/A",('Cash Flow'!G13/(1+$A4)^1+'Cash Flow'!H13/(1+$A4)^2+'Cash Flow'!I13/(1+$A4)^3+'Cash Flow'!J13/(1+$A4)^4+'Cash Flow'!K13/(1+$A4)^5+'Cash Flow'!L13/(1+$A4)^6+('Cash Flow'!L13*(1+F$3)/($A4-F$3))/(1+$A4)^6-Assumptions!B25)/Assumptions!B26) | G4: =IF($A4<=G$3,"N/A",('Cash Flow'!G13/(1+$A4)^1+'Cash Flow'!H13/(1+$A4)^2+'Cash Flow'!I13/(1+$A4)^3+'Cash Flow'!J13/(1+$A4)^4+'Cash Flow'!K13/(1+$A4)^5+'Cash Flow'!L13/(1+$A4)^6+('Cash Flow'!L13*(1+G$3)/($A4-G$3))/(1+$A4)^6-Assumptions!B25)/Assumptions!B26) | H4: =IF($A4<=H$3,"N/A",('Cash Flow'!G13/(1+$A4)^1+'Cash Flow'!H13/(1+$A4)^2+'Cash Flow'!I13/(1+$A4)^3+'Cash Flow'!J13/(1+$A4)^4+'Cash Flow'!K13/(1+$A4)^5+'Cash Flow'!L13/(1+$A4)^6+('Cash Flow'!L13*(1+H$3)/($A4-H$3))/(1+$A4)^6-Assumptions!B25)/Assumptions!B26)
A5: 0.065 | B5: =IF($A5<=B$3,"N/A",('Cash Flow'!G13/(1+$A5)^1+'Cash Flow'!H13/(1+$A5)^2+'Cash Flow'!I13/(1+$A5)^3+'Cash Flow'!J13/(1+$A5)^4+'Cash Flow'!K13/(1+$A5)^5+'Cash Flow'!L13/(1+$A5)^6+('Cash Flow'!L13*(1+B$3)/($A5-B$3))/(1+$A5)^6-Assumptions!B25)/Assumptions!B26) | C5: =IF($A5<=C$3,"N/A",('Cash Flow'!G13/(1+$A5)^1+'Cash Flow'!H13/(1+$A5)^2+'Cash Flow'!I13/(1+$A5)^3+'Cash Flow'!J13/(1+$A5)^4+'Cash Flow'!K13/(1+$A5)^5+'Cash Flow'!L13/(1+$A5)^6+('Cash Flow'!L13*(1+C$3)/($A5-C$3))/(1+$A5)^6-Assumptions!B25)/Assumptions!B26) | D5: =IF($A5<=D$3,"N/A",('Cash Flow'!G13/(1+$A5)^1+'Cash Flow'!H13/(1+$A5)^2+'Cash Flow'!I13/(1+$A5)^3+'Cash Flow'!J13/(1+$A5)^4+'Cash Flow'!K13/(1+$A5)^5+'Cash Flow'!L13/(1+$A5)^6+('Cash Flow'!L13*(1+D$3)/($A5-D$3))/(1+$A5)^6-Assumptions!B25)/Assumptions!B26) | E5: =IF($A5<=E$3,"N/A",('Cash Flow'!G13/(1+$A5)^1+'Cash Flow'!H13/(1+$A5)^2+'Cash Flow'!I13/(1+$A5)^3+'Cash Flow'!J13/(1+$A5)^4+'Cash Flow'!K13/(1+$A5)^5+'Cash Flow'!L13/(1+$A5)^6+('Cash Flow'!L13*(1+E$3)/($A5-E$3))/(1+$A5)^6-Assumptions!B25)/Assumptions!B26) | F5: =IF($A5<=F$3,"N/A",('Cash Flow'!G13/(1+$A5)^1+'Cash Flow'!H13/(1+$A5)^2+'Cash Flow'!I13/(1+$A5)^3+'Cash Flow'!J13/(1+$A5)^4+'Cash Flow'!K13/(1+$A5)^5+'Cash Flow'!L13/(1+$A5)^6+('Cash Flow'!L13*(1+F$3)/($A5-F$3))/(1+$A5)^6-Assumptions!B25)/Assumptions!B26) | G5: =IF($A5<=G$3,"N/A",('Cash Flow'!G13/(1+$A5)^1+'Cash Flow'!H13/(1+$A5)^2+'Cash Flow'!I13/(1+$A5)^3+'Cash Flow'!J13/(1+$A5)^4+'Cash Flow'!K13/(1+$A5)^5+'Cash Flow'!L13/(1+$A5)^6+('Cash Flow'!L13*(1+G$3)/($A5-G$3))/(1+$A5)^6-Assumptions!B25)/Assumptions!B26) | H5: =IF($A5<=H$3,"N/A",('Cash Flow'!G13/(1+$A5)^1+'Cash Flow'!H13/(1+$A5)^2+'Cash Flow'!I13/(1+$A5)^3+'Cash Flow'!J13/(1+$A5)^4+'Cash Flow'!K13/(1+$A5)^5+'Cash Flow'!L13/(1+$A5)^6+('Cash Flow'!L13*(1+H$3)/($A5-H$3))/(1+$A5)^6-Assumptions!B25)/Assumptions!B26)
A6: 0.07 | B6: =IF($A6<=B$3,"N/A",('Cash Flow'!G13/(1+$A6)^1+'Cash Flow'!H13/(1+$A6)^2+'Cash Flow'!I13/(1+$A6)^3+'Cash Flow'!J13/(1+$A6)^4+'Cash Flow'!K13/(1+$A6)^5+'Cash Flow'!L13/(1+$A6)^6+('Cash Flow'!L13*(1+B$3)/($A6-B$3))/(1+$A6)^6-Assumptions!B25)/Assumptions!B26) | C6: =IF($A6<=C$3,"N/A",('Cash Flow'!G13/(1+$A6)^1+'Cash Flow'!H13/(1+$A6)^2+'Cash Flow'!I13/(1+$A6)^3+'Cash Flow'!J13/(1+$A6)^4+'Cash Flow'!K13/(1+$A6)^5+'Cash Flow'!L13/(1+$A6)^6+('Cash Flow'!L13*(1+C$3)/($A6-C$3))/(1+$A6)^6-Assumptions!B25)/Assumptions!B26) | D6: =IF($A6<=D$3,"N/A",('Cash Flow'!G13/(1+$A6)^1+'Cash Flow'!H13/(1+$A6)^2+'Cash Flow'!I13/(1+$A6)^3+'Cash Flow'!J13/(1+$A6)^4+'Cash Flow'!K13/(1+$A6)^5+'Cash Flow'!L13/(1+$A6)^6+('Cash Flow'!L13*(1+D$3)/($A6-D$3))/(1+$A6)^6-Assumptions!B25)/Assumptions!B26) | E6: =IF($A6<=E$3,"N/A",('Cash Flow'!G13/(1+$A6)^1+'Cash Flow'!H13/(1+$A6)^2+'Cash Flow'!I13/(1+$A6)^3+'Cash Flow'!J13/(1+$A6)^4+'Cash Flow'!K13/(1+$A6)^5+'Cash Flow'!L13/(1+$A6)^6+('Cash Flow'!L13*(1+E$3)/($A6-E$3))/(1+$A6)^6-Assumptions!B25)/Assumptions!B26) | F6: =IF($A6<=F$3,"N/A",('Cash Flow'!G13/(1+$A6)^1+'Cash Flow'!H13/(1+$A6)^2+'Cash Flow'!I13/(1+$A6)^3+'Cash Flow'!J13/(1+$A6)^4+'Cash Flow'!K13/(1+$A6)^5+'Cash Flow'!L13/(1+$A6)^6+('Cash Flow'!L13*(1+F$3)/($A6-F$3))/(1+$A6)^6-Assumptions!B25)/Assumptions!B26) | G6: =IF($A6<=G$3,"N/A",('Cash Flow'!G13/(1+$A6)^1+'Cash Flow'!H13/(1+$A6)^2+'Cash Flow'!I13/(1+$A6)^3+'Cash Flow'!J13/(1+$A6)^4+'Cash Flow'!K13/(1+$A6)^5+'Cash Flow'!L13/(1+$A6)^6+('Cash Flow'!L13*(1+G$3)/($A6-G$3))/(1+$A6)^6-Assumptions!B25)/Assumptions!B26) | H6: =IF($A6<=H$3,"N/A",('Cash Flow'!G13/(1+$A6)^1+'Cash Flow'!H13/(1+$A6)^2+'Cash Flow'!I13/(1+$A6)^3+'Cash Flow'!J13/(1+$A6)^4+'Cash Flow'!K13/(1+$A6)^5+'Cash Flow'!L13/(1+$A6)^6+('Cash Flow'!L13*(1+H$3)/($A6-H$3))/(1+$A6)^6-Assumptions!B25)/Assumptions!B26)
A7: 0.075 | B7: =IF($A7<=B$3,"N/A",('Cash Flow'!G13/(1+$A7)^1+'Cash Flow'!H13/(1+$A7)^2+'Cash Flow'!I13/(1+$A7)^3+'Cash Flow'!J13/(1+$A7)^4+'Cash Flow'!K13/(1+$A7)^5+'Cash Flow'!L13/(1+$A7)^6+('Cash Flow'!L13*(1+B$3)/($A7-B$3))/(1+$A7)^6-Assumptions!B25)/Assumptions!B26) | C7: =IF($A7<=C$3,"N/A",('Cash Flow'!G13/(1+$A7)^1+'Cash Flow'!H13/(1+$A7)^2+'Cash Flow'!I13/(1+$A7)^3+'Cash Flow'!J13/(1+$A7)^4+'Cash Flow'!K13/(1+$A7)^5+'Cash Flow'!L13/(1+$A7)^6+('Cash Flow'!L13*(1+C$3)/($A7-C$3))/(1+$A7)^6-Assumptions!B25)/Assumptions!B26) | D7: =IF($A7<=D$3,"N/A",('Cash Flow'!G13/(1+$A7)^1+'Cash Flow'!H13/(1+$A7)^2+'Cash Flow'!I13/(1+$A7)^3+'Cash Flow'!J13/(1+$A7)^4+'Cash Flow'!K13/(1+$A7)^5+'Cash Flow'!L13/(1+$A7)^6+('Cash Flow'!L13*(1+D$3)/($A7-D$3))/(1+$A7)^6-Assumptions!B25)/Assumptions!B26) | E7: =IF($A7<=E$3,"N/A",('Cash Flow'!G13/(1+$A7)^1+'Cash Flow'!H13/(1+$A7)^2+'Cash Flow'!I13/(1+$A7)^3+'Cash Flow'!J13/(1+$A7)^4+'Cash Flow'!K13/(1+$A7)^5+'Cash Flow'!L13/(1+$A7)^6+('Cash Flow'!L13*(1+E$3)/($A7-E$3))/(1+$A7)^6-Assumptions!B25)/Assumptions!B26) | F7: =IF($A7<=F$3,"N/A",('Cash Flow'!G13/(1+$A7)^1+'Cash Flow'!H13/(1+$A7)^2+'Cash Flow'!I13/(1+$A7)^3+'Cash Flow'!J13/(1+$A7)^4+'Cash Flow'!K13/(1+$A7)^5+'Cash Flow'!L13/(1+$A7)^6+('Cash Flow'!L13*(1+F$3)/($A7-F$3))/(1+$A7)^6-Assumptions!B25)/Assumptions!B26) | G7: =IF($A7<=G$3,"N/A",('Cash Flow'!G13/(1+$A7)^1+'Cash Flow'!H13/(1+$A7)^2+'Cash Flow'!I13/(1+$A7)^3+'Cash Flow'!J13/(1+$A7)^4+'Cash Flow'!K13/(1+$A7)^5+'Cash Flow'!L13/(1+$A7)^6+('Cash Flow'!L13*(1+G$3)/($A7-G$3))/(1+$A7)^6-Assumptions!B25)/Assumptions!B26) | H7: =IF($A7<=H$3,"N/A",('Cash Flow'!G13/(1+$A7)^1+'Cash Flow'!H13/(1+$A7)^2+'Cash Flow'!I13/(1+$A7)^3+'Cash Flow'!J13/(1+$A7)^4+'Cash Flow'!K13/(1+$A7)^5+'Cash Flow'!L13/(1+$A7)^6+('Cash Flow'!L13*(1+H$3)/($A7-H$3))/(1+$A7)^6-Assumptions!B25)/Assumptions!B26)
A8: 0.08 | B8: =IF($A8<=B$3,"N/A",('Cash Flow'!G13/(1+$A8)^1+'Cash Flow'!H13/(1+$A8)^2+'Cash Flow'!I13/(1+$A8)^3+'Cash Flow'!J13/(1+$A8)^4+'Cash Flow'!K13/(1+$A8)^5+'Cash Flow'!L13/(1+$A8)^6+('Cash Flow'!L13*(1+B$3)/($A8-B$3))/(1+$A8)^6-Assumptions!B25)/Assumptions!B26) | C8: =IF($A8<=C$3,"N/A",('Cash Flow'!G13/(1+$A8)^1+'Cash Flow'!H13/(1+$A8)^2+'Cash Flow'!I13/(1+$A8)^3+'Cash Flow'!J13/(1+$A8)^4+'Cash Flow'!K13/(1+$A8)^5+'Cash Flow'!L13/(1+$A8)^6+('Cash Flow'!L13*(1+C$3)/($A8-C$3))/(1+$A8)^6-Assumptions!B25)/Assumptions!B26) | D8: =IF($A8<=D$3,"N/A",('Cash Flow'!G13/(1+$A8)^1+'Cash Flow'!H13/(1+$A8)^2+'Cash Flow'!I13/(1+$A8)^3+'Cash Flow'!J13/(1+$A8)^4+'Cash Flow'!K13/(1+$A8)^5+'Cash Flow'!L13/(1+$A8)^6+('Cash Flow'!L13*(1+D$3)/($A8-D$3))/(1+$A8)^6-Assumptions!B25)/Assumptions!B26) | E8: =IF($A8<=E$3,"N/A",('Cash Flow'!G13/(1+$A8)^1+'Cash Flow'!H13/(1+$A8)^2+'Cash Flow'!I13/(1+$A8)^3+'Cash Flow'!J13/(1+$A8)^4+'Cash Flow'!K13/(1+$A8)^5+'Cash Flow'!L13/(1+$A8)^6+('Cash Flow'!L13*(1+E$3)/($A8-E$3))/(1+$A8)^6-Assumptions!B25)/Assumptions!B26) | F8: =IF($A8<=F$3,"N/A",('Cash Flow'!G13/(1+$A8)^1+'Cash Flow'!H13/(1+$A8)^2+'Cash Flow'!I13/(1+$A8)^3+'Cash Flow'!J13/(1+$A8)^4+'Cash Flow'!K13/(1+$A8)^5+'Cash Flow'!L13/(1+$A8)^6+('Cash Flow'!L13*(1+F$3)/($A8-F$3))/(1+$A8)^6-Assumptions!B25)/Assumptions!B26) | G8: =IF($A8<=G$3,"N/A",('Cash Flow'!G13/(1+$A8)^1+'Cash Flow'!H13/(1+$A8)^2+'Cash Flow'!I13/(1+$A8)^3+'Cash Flow'!J13/(1+$A8)^4+'Cash Flow'!K13/(1+$A8)^5+'Cash Flow'!L13/(1+$A8)^6+('Cash Flow'!L13*(1+G$3)/($A8-G$3))/(1+$A8)^6-Assumptions!B25)/Assumptions!B26) | H8: =IF($A8<=H$3,"N/A",('Cash Flow'!G13/(1+$A8)^1+'Cash Flow'!H13/(1+$A8)^2+'Cash Flow'!I13/(1+$A8)^3+'Cash Flow'!J13/(1+$A8)^4+'Cash Flow'!K13/(1+$A8)^5+'Cash Flow'!L13/(1+$A8)^6+('Cash Flow'!L13*(1+H$3)/($A8-H$3))/(1+$A8)^6-Assumptions!B25)/Assumptions!B26)
A9: 0.085 | B9: =IF($A9<=B$3,"N/A",('Cash Flow'!G13/(1+$A9)^1+'Cash Flow'!H13/(1+$A9)^2+'Cash Flow'!I13/(1+$A9)^3+'Cash Flow'!J13/(1+$A9)^4+'Cash Flow'!K13/(1+$A9)^5+'Cash Flow'!L13/(1+$A9)^6+('Cash Flow'!L13*(1+B$3)/($A9-B$3))/(1+$A9)^6-Assumptions!B25)/Assumptions!B26) | C9: =IF($A9<=C$3,"N/A",('Cash Flow'!G13/(1+$A9)^1+'Cash Flow'!H13/(1+$A9)^2+'Cash Flow'!I13/(1+$A9)^3+'Cash Flow'!J13/(1+$A9)^4+'Cash Flow'!K13/(1+$A9)^5+'Cash Flow'!L13/(1+$A9)^6+('Cash Flow'!L13*(1+C$3)/($A9-C$3))/(1+$A9)^6-Assumptions!B25)/Assumptions!B26) | D9: =IF($A9<=D$3,"N/A",('Cash Flow'!G13/(1+$A9)^1+'Cash Flow'!H13/(1+$A9)^2+'Cash Flow'!I13/(1+$A9)^3+'Cash Flow'!J13/(1+$A9)^4+'Cash Flow'!K13/(1+$A9)^5+'Cash Flow'!L13/(1+$A9)^6+('Cash Flow'!L13*(1+D$3)/($A9-D$3))/(1+$A9)^6-Assumptions!B25)/Assumptions!B26) | E9: =IF($A9<=E$3,"N/A",('Cash Flow'!G13/(1+$A9)^1+'Cash Flow'!H13/(1+$A9)^2+'Cash Flow'!I13/(1+$A9)^3+'Cash Flow'!J13/(1+$A9)^4+'Cash Flow'!K13/(1+$A9)^5+'Cash Flow'!L13/(1+$A9)^6+('Cash Flow'!L13*(1+E$3)/($A9-E$3))/(1+$A9)^6-Assumptions!B25)/Assumptions!B26) | F9: =IF($A9<=F$3,"N/A",('Cash Flow'!G13/(1+$A9)^1+'Cash Flow'!H13/(1+$A9)^2+'Cash Flow'!I13/(1+$A9)^3+'Cash Flow'!J13/(1+$A9)^4+'Cash Flow'!K13/(1+$A9)^5+'Cash Flow'!L13/(1+$A9)^6+('Cash Flow'!L13*(1+F$3)/($A9-F$3))/(1+$A9)^6-Assumptions!B25)/Assumptions!B26) | G9: =IF($A9<=G$3,"N/A",('Cash Flow'!G13/(1+$A9)^1+'Cash Flow'!H13/(1+$A9)^2+'Cash Flow'!I13/(1+$A9)^3+'Cash Flow'!J13/(1+$A9)^4+'Cash Flow'!K13/(1+$A9)^5+'Cash Flow'!L13/(1+$A9)^6+('Cash Flow'!L13*(1+G$3)/($A9-G$3))/(1+$A9)^6-Assumptions!B25)/Assumptions!B26) | H9: =IF($A9<=H$3,"N/A",('Cash Flow'!G13/(1+$A9)^1+'Cash Flow'!H13/(1+$A9)^2+'Cash Flow'!I13/(1+$A9)^3+'Cash Flow'!J13/(1+$A9)^4+'Cash Flow'!K13/(1+$A9)^5+'Cash Flow'!L13/(1+$A9)^6+('Cash Flow'!L13*(1+H$3)/($A9-H$3))/(1+$A9)^6-Assumptions!B25)/Assumptions!B26)
A10: 0.09 | B10: =IF($A10<=B$3,"N/A",('Cash Flow'!G13/(1+$A10)^1+'Cash Flow'!H13/(1+$A10)^2+'Cash Flow'!I13/(1+$A10)^3+'Cash Flow'!J13/(1+$A10)^4+'Cash Flow'!K13/(1+$A10)^5+'Cash Flow'!L13/(1+$A10)^6+('Cash Flow'!L13*(1+B$3)/($A10-B$3))/(1+$A10)^6-Assumptions!B25)/Assumptions!B26) | C10: =IF($A10<=C$3,"N/A",('Cash Flow'!G13/(1+$A10)^1+'Cash Flow'!H13/(1+$A10)^2+'Cash Flow'!I13/(1+$A10)^3+'Cash Flow'!J13/(1+$A10)^4+'Cash Flow'!K13/(1+$A10)^5+'Cash Flow'!L13/(1+$A10)^6+('Cash Flow'!L13*(1+C$3)/($A10-C$3))/(1+$A10)^6-Assumptions!B25)/Assumptions!B26) | D10: =IF($A10<=D$3,"N/A",('Cash Flow'!G13/(1+$A10)^1+'Cash Flow'!H13/(1+$A10)^2+'Cash Flow'!I13/(1+$A10)^3+'Cash Flow'!J13/(1+$A10)^4+'Cash Flow'!K13/(1+$A10)^5+'Cash Flow'!L13/(1+$A10)^6+('Cash Flow'!L13*(1+D$3)/($A10-D$3))/(1+$A10)^6-Assumptions!B25)/Assumptions!B26) | E10: =IF($A10<=E$3,"N/A",('Cash Flow'!G13/(1+$A10)^1+'Cash Flow'!H13/(1+$A10)^2+'Cash Flow'!I13/(1+$A10)^3+'Cash Flow'!J13/(1+$A10)^4+'Cash Flow'!K13/(1+$A10)^5+'Cash Flow'!L13/(1+$A10)^6+('Cash Flow'!L13*(1+E$3)/($A10-E$3))/(1+$A10)^6-Assumptions!B25)/Assumptions!B26) | F10: =IF($A10<=F$3,"N/A",('Cash Flow'!G13/(1+$A10)^1+'Cash Flow'!H13/(1+$A10)^2+'Cash Flow'!I13/(1+$A10)^3+'Cash Flow'!J13/(1+$A10)^4+'Cash Flow'!K13/(1+$A10)^5+'Cash Flow'!L13/(1+$A10)^6+('Cash Flow'!L13*(1+F$3)/($A10-F$3))/(1+$A10)^6-Assumptions!B25)/Assumptions!B26) | G10: =IF($A10<=G$3,"N/A",('Cash Flow'!G13/(1+$A10)^1+'Cash Flow'!H13/(1+$A10)^2+'Cash Flow'!I13/(1+$A10)^3+'Cash Flow'!J13/(1+$A10)^4+'Cash Flow'!K13/(1+$A10)^5+'Cash Flow'!L13/(1+$A10)^6+('Cash Flow'!L13*(1+G$3)/($A10-G$3))/(1+$A10)^6-Assumptions!B25)/Assumptions!B26) | H10: =IF($A10<=H$3,"N/A",('Cash Flow'!G13/(1+$A10)^1+'Cash Flow'!H13/(1+$A10)^2+'Cash Flow'!I13/(1+$A10)^3+'Cash Flow'!J13/(1+$A10)^4+'Cash Flow'!K13/(1+$A10)^5+'Cash Flow'!L13/(1+$A10)^6+('Cash Flow'!L13*(1+H$3)/($A10-H$3))/(1+$A10)^6-Assumptions!B25)/Assumptions!B26)
A12: Yellow = base case (WACC≈7.16%, TGR=2.0%). 'N/A' = WACC ≤ TGR (terminal value undefined). Read across rows for TGR sensitivity; down columns for WACC sensitivity. Stress: WACC at 8.5% (leverage scenario) sharply reduces implied price.

Sheet Dashboard
A1: LUFTHANSA GROUP (LHA.DE) · INTEGRATED FINANCIAL VALUATION & FORECASTING MODEL · v4.0 · July 2026
A2: Analyst: Emmanuel Sarpong | EUR (€ millions) | Data: LH Annual Reports 2020–2024 + LH IR | github.com/emmasarps/lufthansa-financial-valuation-model
A4: ◾ 2024 ACTUALS · KEY PERFORMANCE INDICATORS (all verified — LH Annual Report 2024 / LH IR website)
A5: REVENUE (€M) | C5: EBITDA (€M) | E5: EBIT (€M) | G5: NET INCOME (€M) | I5: NET DEBT (€M) | K5: DCF IMPLIED PRICE (€)
A6: ='Income Statement'!F3 | C6: ='Income Statement'!F6 | E6: ='Income Statement'!F4 | G6: ='Income Statement'!F10 | I6: =Assumptions!B25 | K6: ='DCF Valuation'!B23
A7: ="▲ "&TEXT(Assumptions!F4,"0.0%")&" vs FY2023" | C7: ="Margin: "&TEXT('Income Statement'!F14,"0.0%") | E7: ="Margin: "&TEXT('Income Statement'!F13,"0.0%") | G7: ="Net Margin: "&TEXT('Income Statement'!F15,"0.0%") | I7: ="ND / EBITDA: "&TEXT(Assumptions!B25/'Income Statement'!F6,"0.0x") | K7: ="vs €"&TEXT(Assumptions!B27,"0.00")&" mkt · "&TEXT('DCF Valuation'!B25,"0.0%")&" upside"
A9: ◾ FINANCIAL PERFORMANCE SUMMARY · 2020A – 2024A Verified Historical · 2025E – 2030E Forecast
A10: Metric | B10: 2020A | C10: 2021A | D10: 2022A | E10: 2023A | F10: 2024A | G10: 2025E | H10: 2026E | I10: 2027E | J10: 2028E | K10: 2029E | L10: 2030E
A11: Revenue (€M) | B11: ='Income Statement'!B3 | C11: ='Income Statement'!C3 | D11: ='Income Statement'!D3 | E11: ='Income Statement'!E3 | F11: ='Income Statement'!F3 | G11: ='Income Statement'!G3 | H11: ='Income Statement'!H3 | I11: ='Income Statement'!I3 | ... L11: ='Income Statement'!L3
A12: Revenue Growth % | B12: =IF(ISNUMBER(Assumptions!B4),Assumptions!B4,"-") | C12: =IF(ISNUMBER(Assumptions!C4),Assumptions!C4,"-") | D12: =IF(ISNUMBER(Assumptions!D4),Assumptions!D4,"-") | E12: =IF(ISNUMBER(Assumptions!E4),Assumptions!E4,"-") | F12: =IF(ISNUMBER(Assumptions!F4),Assumptions!F4,"-") | G12: =IF(ISNUMBER(Assumptions!G4),Assumptions!G4,"-") | H12: =IF(ISNUMBER(Assumptions!H4),Assumptions!H4,"-") | I12: =IF(ISNUMBER(Assumptions!I4),Assumptions!I4,"-") | ... L12: =IF(ISNUMBER(Assumptions!L4),Assumptions!L4,"-")
A13: EBITDA Margin % | B13: ='Income Statement'!B14 | C13: ='Income Statement'!C14 | D13: ='Income Statement'!D14 | E13: ='Income Statement'!E14 | F13: ='Income Statement'!F14 | G13: ='Income Statement'!G14 | H13: ='Income Statement'!H14 | I13: ='Income Statement'!I14 | ... L13: ='Income Statement'!L14
A14: EBIT Margin % | B14: ='Income Statement'!B13 | C14: ='Income Statement'!C13 | D14: ='Income Statement'!D13 | E14: ='Income Statement'!E13 | F14: ='Income Statement'!F13 | G14: ='Income Statement'!G13 | H14: ='Income Statement'!H13 | I14: ='Income Statement'!I13 | ... L14: ='Income Statement'!L13
A15: Net Margin % | B15: ='Income Statement'!B15 | C15: ='Income Statement'!C15 | D15: ='Income Statement'!D15 | E15: ='Income Statement'!E15 | F15: ='Income Statement'!F15 | G15: ='Income Statement'!G15 | H15: ='Income Statement'!H15 | I15: ='Income Statement'!I15 | ... L15: ='Income Statement'!L15
A17: ◾ DCF VALUATION — EQUITY BRIDGE | G17: ◾ COMPARABLE COMPANY ANALYSIS (EV/EBITDA, FY2024A)
A18: Sum of PV FCFFs (2025E–2030E) | D18: ='DCF Valuation'!B17 | G18: Company | H18: Mkt Cap | I18: EV (€M) | J18: EV/EBITDA | K18: P/E
A19: PV of Terminal Value (Gordon Growth) | D19: ='DCF Valuation'!B18 | G19: Lufthansa (LHA.DE) | H19: =Comparables!B3 | I19: =Comparables!D3 | J19: =Comparables!G3 | K19: =Comparables!H3
A20: Enterprise Value (EV) | D20: ='DCF Valuation'!B19 | G20: Ryanair | H20: =Comparables!B4 | I20: =Comparables!D4 | J20: =Comparables!G4 | K20: =Comparables!H4
A21: Less: Net Debt (2024A verified) | D21: =Assumptions!B25 | G21: IAG | H21: =Comparables!B5 | I21: =Comparables!D5 | J21: =Comparables!G5 | K21: =Comparables!H5
A22: Equity Value | D22: ='DCF Valuation'!B21 | G22: Air France-KLM | H22: =Comparables!B6 | I22: =Comparables!D6 | J22: =Comparables!G6 | K22: =Comparables!H6
A23: ÷ Shares Outstanding (M) | D23: =Assumptions!B26 | G23: easyJet | H23: =Comparables!B7 | I23: =Comparables!D7 | J23: =Comparables!G7 | K23: =Comparables!H7
A24: DCF Implied Share Price (€) | D24: ='DCF Valuation'!B23 | G24: Median (ex-LH) | H24: =Comparables!B8 | I24: =Comparables!D8 | J24: =Comparables!G8 | K24: =Comparables!H8
A25: Reference: 2024 Year-End Price (€) | D25: =Assumptions!B27 | G25: Comps-Implied Share Price (€) | J25: =Comparables!B18
A26: WACC (build-up: Ke×We + Kd(AT)×Wd) | D26: =Assumptions!B21
A27: Terminal Growth Rate | D27: =Assumptions!B22
A29: ◾ SENSITIVITY ANALYSIS · Implied Share Price (€) | WACC × Terminal Growth Rate | Yellow = base case
A30: WACC ╲ TGR → | B30: 1.5% | C30: 2.0% | D30: 2.5% | E30: 3.0% | F30: 3.5% | G30: Values from Sensitivity sheet. Yellow = base case (WACC≈7.2%, TGR=2.0%)
A31: 6.5% | B31: =Sensitivity!C5 | C31: =Sensitivity!D5 | D31: =Sensitivity!E5 | E31: =Sensitivity!F5 | F31: =Sensitivity!G5
A32: 7.0% | B32: =Sensitivity!C6 | C32: =Sensitivity!D6 | D32: =Sensitivity!E6 | E32: =Sensitivity!F6 | F32: =Sensitivity!G6
A33: 7.5% | B33: =Sensitivity!C7 | C33: =Sensitivity!D7 | D33: =Sensitivity!E7 | E33: =Sensitivity!F7 | F33: =Sensitivity!G7
A34: 8.0% | B34: =Sensitivity!C8 | C34: =Sensitivity!D8 | D34: =Sensitivity!E8 | E34: =Sensitivity!F8 | F34: =Sensitivity!G8
A35: 8.5% | B35: =Sensitivity!C9 | C35: =Sensitivity!D9 | D35: =Sensitivity!E9 | E35: =Sensitivity!F9 | F35: =Sensitivity!G9
A37: DATA VERIFICATION STATUS: Revenue / EBIT / NI 2022–2024 ✓ verified from LH Annual Reports & LH IR. 2022 equity ≈ €8,500M (OCI pension remeasurement — simplified model keeps as estimated). Comps multiples: approximate Q4 2024 — re-verify before use. WACC inputs: Rf=2.5% (Bundesbank 2024 avg), β=1.20 (LHA.DE 5Y monthly), ERP=5.5% (Damodaran Jan-2024). This dashboard is fully linked to the underlying model — change any input to see all outputs update automatically.
